<?xml version="1.0" encoding="UTF-8"?>
<!DOCTYPE mapper PUBLIC "-//mybatis.org//DTD Mapper 3.0//EN" "http://mybatis.org/dtd/mybatis-3-mapper.dtd">
<mapper namespace="com.sunyard.ars.system.dao.mc.McFieldMapper">
  <resultMap id="BaseResultMap" type="com.sunyard.ars.system.pojo.mc.McField">
     <!--
      WARNING - @mbg.generated
      This element is automatically generated by MyBatis Generator, do not modify.
    -->
    <id column="ID" jdbcType="INTEGER" property="id" />
    <result column="NAME" jdbcType="VARCHAR" property="name" />
    <result column="CH_NAME" jdbcType="VARCHAR" property="chName" />
    <result column="TYPE" jdbcType="CHAR" property="type" />
    <result column="LENGTH" jdbcType="VARCHAR" property="length" />
    <result column="SCALE" jdbcType="VARCHAR" property="scale" />
    <result column="SPREC" jdbcType="VARCHAR" property="sprec" />
    <result column="ISNULL" jdbcType="CHAR" property="isnull" />
    <result column="DEFVALUE" jdbcType="VARCHAR" property="defvalue" />
    <result column="LIMITED" jdbcType="CHAR" property="limited" />
    <result column="TABLE_TYPE" jdbcType="CHAR" property="tableType" />
    <result column="HASDIC" jdbcType="CHAR" property="hasDic" />
    <result column="DICNAME" jdbcType="VARCHAR" property="dicName" />
    <result column="IS_INDEX" jdbcType="CHAR" property="isIndex" />
  </resultMap>
  
  <resultMap id="FieldNameMap" type="com.sunyard.ars.system.pojo.mc.McField">
    <!--
      WARNING - @mbg.generated
      This element is automatically generated by MyBatis Generator, do not modify.
    -->
    <id column="ID" jdbcType="INTEGER" property="id" />
    <result column="NAME" jdbcType="VARCHAR" property="name" />
    <result column="CH_NAME" jdbcType="VARCHAR" property="chName" />
  </resultMap>
  
  <sql id="Base_Column_List">
    <!--
      WARNING - @mbg.generated
      This element is automatically generated by MyBatis Generator, do not modify.
    -->
    ID, NAME, CH_NAME, TYPE, LENGTH, SCALE, SPREC, ISNULL, DEFVALUE, LIMITED, TABLE_TYPE,HASDIC,DICNAME,IS_INDEX
  </sql>
  <select id="selectByPrimaryKey" parameterType="java.lang.Integer" resultMap="BaseResultMap">
    <!--
      WARNING - @mbg.generated
      This element is automatically generated by MyBatis Generator, do not modify.
    -->
    select 
    <include refid="Base_Column_List" />
    from MC_FIELD_TB
    where ID = #{id,jdbcType=INTEGER}
  </select>
  <delete id="deleteByPrimaryKey" parameterType="java.lang.Integer">
    <!--
      WARNING - @mbg.generated
      This element is automatically generated by MyBatis Generator, do not modify.
    -->
    delete from MC_FIELD_TB
    where ID = #{id,jdbcType=INTEGER}
  </delete>
  <insert id="insert" parameterType="com.sunyard.ars.system.pojo.mc.McField">
    <!--
      WARNING - @mbg.generated
      This element is automatically generated by MyBatis Generator, do not modify.
    -->
    insert into MC_FIELD_TB (ID, NAME, CH_NAME, 
      TYPE, LENGTH, SCALE, SPREC, 
      ISNULL, DEFVALUE, LIMITED, 
      TABLE_TYPE, IS_INDEX)
    values (#{id,jdbcType=INTEGER}, #{name,jdbcType=VARCHAR}, #{chName,jdbcType=VARCHAR}, 
      #{type,jdbcType=CHAR}, #{length,jdbcType=VARCHAR}, #{scale,jdbcType=VARCHAR}, #{sprec,jdbcType=VARCHAR}, 
      #{isnull,jdbcType=CHAR}, #{defvalue,jdbcType=VARCHAR}, #{limited,jdbcType=CHAR}, 
      #{tableType,jdbcType=CHAR},#{isIndex,jdbcType=CHAR})
  </insert>
  <insert id="insertSelective" parameterType="com.sunyard.ars.system.pojo.mc.McField">
  <selectKey resultType="INTEGER" order="BEFORE" keyProperty="id">  
      select  case when max(id)+1 is null  then 1 else max(id)+1 end  as id from MC_FIELD_TB
  	 </selectKey> 
    insert into MC_FIELD_TB
    <trim prefix="(" suffix=")" suffixOverrides=",">
        ID,
      <if test="name != null">
        NAME,
      </if>
      <if test="chName != null">
        CH_NAME,
      </if>
      <if test="type != null">
        TYPE,
      </if>
      <if test="length != null">
        LENGTH,
      </if>
      <if test="scale != null">
        SCALE,
      </if>
      <if test="sprec != null">
        SPREC,
      </if>
      <if test="isnull != null">
        ISNULL,
      </if>
      <if test="defvalue != null">
        DEFVALUE,
      </if>
      <if test="limited != null">
        LIMITED,
      </if>
      <if test="tableType != null">
        TABLE_TYPE,
      </if>
      <if test="hasDic != null">
        HASDIC,
      </if>
      <if test="dicName != null">
        DICNAME,
      </if>
      <if test="isIndex != null">
        IS_INDEX,
      </if>
    </trim>
    <trim prefix="values (" suffix=")" suffixOverrides=",">
        #{id,jdbcType=INTEGER},
      <if test="name != null">
        #{name,jdbcType=VARCHAR},
      </if>
      <if test="chName != null">
        #{chName,jdbcType=VARCHAR},
      </if>
      <if test="type != null">
        #{type,jdbcType=CHAR},
      </if>
      <if test="length != null">
        #{length,jdbcType=VARCHAR},
      </if>
      <if test="scale != null">
        #{scale,jdbcType=VARCHAR},
      </if>
      <if test="sprec != null">
        #{sprec,jdbcType=VARCHAR},
      </if>
      <if test="isnull != null">
        #{isnull,jdbcType=CHAR},
      </if>
      <if test="defvalue != null">
        #{defvalue,jdbcType=VARCHAR},
      </if>
      <if test="limited != null">
        #{limited,jdbcType=CHAR},
      </if>
      <if test="tableType != null">
        #{tableType,jdbcType=CHAR},
      </if>
      <if test="hasDic != null">
        #{hasDic,jdbcType=CHAR},
      </if>
      <if test="dicName != null">
        #{dicName,jdbcType=VARCHAR},
      </if>
      <if test="isIndex != null">
        #{isIndex,jdbcType=CHAR},
      </if>
    </trim>
  </insert>
  <update id="updateByPrimaryKeySelective" parameterType="com.sunyard.ars.system.pojo.mc.McField">
    <!--
      WARNING - @mbg.generated
      This element is automatically generated by MyBatis Generator, do not modify.
    -->
    update MC_FIELD_TB
    <set>
      <if test="name != null">
        NAME = #{name,jdbcType=VARCHAR},
      </if>
      <if test="chName != null">
        CH_NAME = #{chName,jdbcType=VARCHAR},
      </if>
      <if test="type != null">
        TYPE = #{type,jdbcType=CHAR},
      </if>
      <if test="length != null">
        LENGTH = #{length,jdbcType=VARCHAR},
      </if>
      <if test="scale != null">
        SCALE = #{scale,jdbcType=VARCHAR},
      </if>
      <if test="sprec != null">
        SPREC = #{sprec,jdbcType=VARCHAR},
      </if>
      <if test="isnull != null">
        ISNULL = #{isnull,jdbcType=CHAR},
      </if>
      <if test="defvalue != null">
        DEFVALUE = #{defvalue,jdbcType=VARCHAR},
      </if>
      <if test="limited != null">
        LIMITED = #{limited,jdbcType=CHAR},
      </if>
      <if test="tableType != null">
        TABLE_TYPE = #{tableType,jdbcType=CHAR},
      </if>
      <if test="hasDic != null">
        HASDIC = #{hasDic,jdbcType=CHAR},
      </if>
      <if test="dicName != null">
        DICNAME = #{dicName,jdbcType=VARCHAR},
      </if>
      <if test="isIndex != null">
        IS_INDEX = #{isIndex,jdbcType=CHAR},
      </if>
    </set>
    where ID = #{id,jdbcType=INTEGER}
  </update>
  <update id="updateByPrimaryKey" parameterType="com.sunyard.ars.system.pojo.mc.McField">
    <!--
      WARNING - @mbg.generated
      This element is automatically generated by MyBatis Generator, do not modify.
    -->
    update MC_FIELD_TB
    set NAME = #{name,jdbcType=VARCHAR},
      CH_NAME = #{chName,jdbcType=VARCHAR},
      TYPE = #{type,jdbcType=CHAR},
      LENGTH = #{length,jdbcType=VARCHAR},
      SCALE = #{scale,jdbcType=VARCHAR},
      SPREC = #{sprec,jdbcType=VARCHAR},
      ISNULL = #{isnull,jdbcType=CHAR},
      DEFVALUE = #{defvalue,jdbcType=VARCHAR},
      LIMITED = #{limited,jdbcType=CHAR},
      TABLE_TYPE = #{tableType,jdbcType=CHAR},
      IS_INDEX = #{isIndex,jdbcType=CHAR}
    where ID = #{id,jdbcType=INTEGER}
  </update>
  
  <select id="getFieldByTableId" parameterType="java.lang.Integer" resultMap="FieldNameMap">
	SELECT A.ID,A.NAME,A.CH_NAME FROM MC_FIELD_TB A,MC_TABLE_FIELD_TB B WHERE
		A.ID=B.FIELD_ID AND B.TABLE_ID=#{tableId,jdbcType=INTEGER}
  </select>
  
	<select id="getFieldByName" resultMap="BaseResultMap">
	SELECT   <include refid="Base_Column_List" />
	 FROM MC_FIELD_TB WHERE NAME=#{name,jdbcType=VARCHAR} AND TABLETYPE = #{tableType,jdbcType=CHAR}
	</select>
	
	<select id="getFieldByTableType" resultMap="BaseResultMap">
	SELECT  <include refid="Base_Column_List" /> FROM MC_FIELD_TB WHERE TABLETYPE = #{tableType,jdbcType=CHAR} order by NAME
	</select>
	
	<select id="findSystemFieldByTableId" resultMap="FieldNameMap">
		select b.ID,b.NAME,b.CH_NAME from MC_TABLE_TB a,MC_FIELD_TB b
		 where a.TABLE_TYPE=b.TABLE_TYPE and a.ID=#{tableId,jdbcType=INTEGER}
	</select>
	
	<!--根据条件查询字段表  -->
	<select id="selectBySelective" parameterType="com.sunyard.ars.system.pojo.mc.McField" resultMap="BaseResultMap" >
	select
	   <include refid="Base_Column_List" />
    from MC_FIELD_TB
    <where>
     <if test="name !=null and name !=''">
     AND  NAME = #{name}
     </if>
    <if test="chName !=null and chName != ''">
    AND CH_NAME = #{chName}
    </if>
    <if test="type !=null and type !=''">
    AND TYPE = #{type}
    </if>
      <if test="tableType !=null and tableType !=''">
    AND TABLE_TYPE = #{tableType}
    </if>
    </where>
    order by NAME,ID
	</select>
	
	<!--查询存在该字段的表  -->
	<select id="selectTableNames" resultType="java.lang.String">
	SELECT TABLE_NAME FROM MC_TABLE_TB A JOIN MC_TABLE_FIELD_TB B ON A.ID = B.TABLE_ID WHERE B.FIELD_ID =#{fieldId}
	</select>
	
	<select id="selectTableCol" resultType="java.lang.Integer">
		<if test="dbType == @com.sunyard.ars.common.comm.ARSConstants@DATABASE_TYPE_DB2">
			select count(1) from syscat.columns where tabname=#{tableName} and  COLNAME=#{column}
		</if>
		
		<if test="dbType == @com.sunyard.ars.common.comm.ARSConstants@DATABASE_TYPE_ORACLE">
			select count(1) from user_tab_columns where TABLE_NAME=#{tableName}  and COLUMN_NAME=#{column}
		</if>
	</select>
	
	
	<!--查询系统字段  -->
	<select id="selectSysField" parameterType="java.lang.Integer" resultType="java.util.HashMap" >
	SELECT B.ID,B.NAME,B.CH_NAME FROM MC_TABLE_TB A JOIN  MC_FIELD_TB B ON A.TABLE_TYPE = B.TABLE_TYPE
	WHERE A.ID = #{tableId}
	</select>


  <!--获取必须的模型字段 'ENTRY_ID','ENTRYROW_ID','BUSI_DATA_DATE','ISHANDLE','BANKCODE','PROC_DATE'-->
  <select id="getArmsMustFiedl"  resultMap="BaseResultMap">
      SELECT <include refid="Base_Column_List" />
      FROM MC_FIELD_TB F WHERE F.NAME IN ('BANKCODE','PROC_DATE')
      AND F.TABLE_TYPE IN ('0','5') ORDER BY F.TABLE_TYPE
  </select>
  
  <!-- 根据表类型查询系统字段 -->
  <select id="getMcFieldByTableType" resultMap="BaseResultMap">
  	SELECT <include refid="Base_Column_List" />
			FROM MC_FIELD_TB WHERE TABLE_TYPE= #{tabletype}
  </select>
	
</mapper>